crumpets/__init__.py
crumpets/augmentation.py
crumpets/augmentation_cpu.py
crumpets/broker.py
crumpets/dataloader.py
crumpets/logging.py
crumpets/presets.py
crumpets/procname.py
crumpets/rng.py
crumpets/shm.py
crumpets/timing.py
crumpets/torch/__init__.py
crumpets/torch/augmentation_cuda.py
crumpets/torch/dataloader.py
crumpets/torch/loss.py
crumpets/torch/metrics.py
crumpets/torch/policy.py
crumpets/torch/randomizer.py
crumpets/torch/shm.py
crumpets/torch/trainer.py
crumpets/torch/utils.py
crumpets/workers/__init__.py
crumpets/workers/saliency/__init__.py
crumpets/workers/segmentation/__init__.py
crumpets-3.0.0a5.dist-info/LICENSE
crumpets-3.0.0a5.dist-info/METADATA
crumpets-3.0.0a5.dist-info/WHEEL
crumpets-3.0.0a5.dist-info/top_level.txt
crumpets-3.0.0a5.dist-info/RECORD
