Metadata-Version: 2.1
Name: crumpets
Version: 3.0.0a5
Summary: UNKNOWN
Home-page: UNKNOWN
Author: Joachim Folz
Author-email: joachim.folz@dfki.de
License: UNKNOWN
Project-URL: Documentation, https://crumpets.readthedocs.io
Project-URL: Source, https://gitlab.com/jfolz/crumpets
Project-URL: Tracker, https://gitlab.com/jfolz/crumpets/-/issues
Keywords: crumpets deep-learning saliency prediction
Platform: UNKNOWN
Classifier: Development Status :: 4 - Beta
Classifier: Intended Audience :: Science/Research
Classifier: Programming Language :: Python :: 3.6
Classifier: Programming Language :: Python :: 3.7
Classifier: Programming Language :: Python :: 3.8
Classifier: Programming Language :: Python :: 3.9
Classifier: Programming Language :: Python :: 3.10
Requires-Python: >=3.6.0
License-File: LICENSE
Requires-Dist: msgpack (<=2.0.0,>=0.6.1)
Requires-Dist: msgpack-numpy (<1.0.0,>=0.4.1)
Requires-Dist: numpy (<2.0.0,>=1.11.0)
Requires-Dist: opencv-python-headless (>=4.1.0.25)
Requires-Dist: pyzmq (<23.0.0,>=16.0.0)
Requires-Dist: scipy (<2.0.0,>=0.17.0)
Requires-Dist: simplejpeg (>=1.3.1)
Requires-Dist: tqdm (<=5.0.0,>=4.32.2)
